exchange_data_downloader-0.2.0.dist-info/licenses/LICENSE
exdata/__init__.py
exdata/exceptions.py
exdata/utils.py
exdata/binance/__init__.py
exdata/binance/downloader.py
exdata/binance/types.py
exchange_data_downloader-0.2.0.dist-info/METADATA
exchange_data_downloader-0.2.0.dist-info/WHEEL
exchange_data_downloader-0.2.0.dist-info/top_level.txt
exchange_data_downloader-0.2.0.dist-info/RECORD
