Metadata-Version: 2.4
Name: exchange-data-downloader
Version: 0.2.0
Summary: exchange-data-downloader — простая библиотека для скачивания и распаковки исторических данных с криптовалютных бирж. Поддерживает организацию файлов по папкам, кэширование и разные типы данных (klines, trades, funding и др.). Идеально для бэктестов и аналитики.
Author: LoveBloodAndDiamonds
License: MIT License
Project-URL: Github, https://github.com/LoveBloodAndDiamonds/exchange-data-downloader
Project-URL: Author, https://t.me/LoveBloodAndDiamonds
Requires-Python: >=3.12
License-File: LICENSE
Requires-Dist: loguru>=0.7.3
Dynamic: license-file
